{"stats":{"minecraft:used":{"minecraft:yellow_wool":134,"minecraft:redstone_torch":576,"minecraft:sticky_piston":42,"minecraft:light_gray_wool":11,"minecraft:lever":60,"minecraft:repeater":399,"minecraft:redstone_lamp":12,"minecraft:target":42,"minecraft:comparator":3,"minecraft:red_wool":536,"minecraft:orange_wool":656,"minecraft:green_wool":20,"minecraft:light_blue_wool":259,"minecraft:redstone":2527,"minecraft:slime_block":38,"minecraft:lime_wool":189,"minecraft:blue_wool":708,"minecraft:oak_sign":65,"minecraft:smooth_stone_slab":1648,"minecraft:stone":9,"minecraft:gray_wool":1228,"minecraft:purple_wool":524,"minecraft:obsidian":105},"minecraft:custom":{"minecraft:time_since_rest":227394,"minecraft:damage_taken":1110,"minecraft:crouch_one_cm":11070,"minecraft:play_one_minute":1027249,"minecraft:sprint_one_cm":526366,"minecraft:deaths":4,"minecraft:walk_one_cm":309253,"minecraft:sneak_time":39048,"minecraft:drop":4,"minecraft:jump":4649,"minecraft:leave_game":12,"minecraft:time_since_death":227364,"minecraft:fall_one_cm":1732,"minecraft:fly_one_cm":10650267},"minecraft:picked_up":{"minecraft:redstone_torch":1,"minecraft:light_gray_wool":1},"minecraft:dropped":{"minecraft:redstone_torch":1,"minecraft:light_gray_wool":1,"minecraft:orange_wool":1,"minecraft:light_blue_wool":1}},"DataVersion":2584}